recognizers_date_time/__init__.py
recognizers_date_time/date_time/__init__.py
recognizers_date_time/date_time/base_configs.py
recognizers_date_time/date_time/base_date.py
recognizers_date_time/date_time/base_dateperiod.py
recognizers_date_time/date_time/base_datetime.py
recognizers_date_time/date_time/base_datetimeperiod.py
recognizers_date_time/date_time/base_duration.py
recognizers_date_time/date_time/base_holiday.py
recognizers_date_time/date_time/base_merged.py
recognizers_date_time/date_time/base_set.py
recognizers_date_time/date_time/base_time.py
recognizers_date_time/date_time/base_timeperiod.py
recognizers_date_time/date_time/constants.py
recognizers_date_time/date_time/date_time_recognizer.py
recognizers_date_time/date_time/extractors.py
recognizers_date_time/date_time/models.py
recognizers_date_time/date_time/parsers.py
recognizers_date_time/date_time/utilities.py
recognizers_date_time/date_time/chinese/__init__.py
recognizers_date_time/date_time/chinese/base_date_time_extractor.py
recognizers_date_time/date_time/chinese/date_extractor.py
recognizers_date_time/date_time/chinese/date_extractor_config.py
recognizers_date_time/date_time/chinese/date_parser.py
recognizers_date_time/date_time/chinese/date_parser_config.py
recognizers_date_time/date_time/chinese/dateperiod_extractor.py
recognizers_date_time/date_time/chinese/dateperiod_extractor_config.py
recognizers_date_time/date_time/chinese/dateperiod_parser.py
recognizers_date_time/date_time/chinese/dateperiod_parser_config.py
recognizers_date_time/date_time/chinese/datetime_extractor.py
recognizers_date_time/date_time/chinese/datetime_extractor_config.py
recognizers_date_time/date_time/chinese/datetime_parser.py
recognizers_date_time/date_time/chinese/datetime_parser_config.py
recognizers_date_time/date_time/chinese/datetimeperiod_extractor.py
recognizers_date_time/date_time/chinese/datetimeperiod_extractor_config.py
recognizers_date_time/date_time/chinese/datetimeperiod_parser.py
recognizers_date_time-1.0.0a1.dist-info/METADATA
recognizers_date_time-1.0.0a1.dist-info/WHEEL
recognizers_date_time-1.0.0a1.dist-info/top_level.txt
recognizers_date_time-1.0.0a1.dist-info/RECORD
